vkauth/__init__.py
vkauth/vkauth.py
vkauth-1.0.0.dist-info/LICENSE
vkauth-1.0.0.dist-info/METADATA
vkauth-1.0.0.dist-info/WHEEL
vkauth-1.0.0.dist-info/top_level.txt
vkauth-1.0.0.dist-info/RECORD
