Metadata-Version: 2.1
Name: vkauth
Version: 1.0.0
Summary: Library that helps you to authenticate with VK.com using cookies from your browser. The library automatically fetches required cookies from supported browsers, establishes a session, and retrieves an access token
Home-page: https://github.com/DedInc/vkauth
Author: Maehdakvan
Author-email: visitanimation@google.com
Project-URL: Bug Tracker, https://github.com/DedInc/vkauth/issues
Classifier: Programming Language :: Python :: 3
Classifier: License :: OSI Approved :: MIT License
Classifier: Operating System :: OS Independent
Requires-Python: >=3.6
License-File: LICENSE
Requires-Dist: psutil
Requires-Dist: requests
Requires-Dist: browser-cookie-3x
